twitter_user_emulator/__init__.py
twitter_user_emulator/download_tweets.py
twitter_user_emulator/emulator.py
twitter_user_emulator/preprocessor.py
twitter_user_emulator-0.0.2.dist-info/LICENSE
twitter_user_emulator-0.0.2.dist-info/METADATA
twitter_user_emulator-0.0.2.dist-info/WHEEL
twitter_user_emulator-0.0.2.dist-info/top_level.txt
twitter_user_emulator-0.0.2.dist-info/RECORD
