Metadata-Version: 2.1
Name: twitter-user-emulator
Version: 0.0.2
Summary: Twitter-User Emulating Tweet Generator
Home-page: https://github.com/equ1/twitter_user_emulator
Author: Rushat Rai
Author-email: rushatrai@gmail.com
License: MIT
Keywords: deep-learning,gpt-2,twitter
Platform: UNKNOWN
Requires-Python: >=3.6
Requires-Dist: gpt-2-simple
Requires-Dist: pandas
Requires-Dist: Scweet
